handsdown/README.md
handsdown/__init__.py
handsdown/__main__.py
handsdown/ast_parser/__init__.py
handsdown/ast_parser/analyzers/__init__.py
handsdown/ast_parser/analyzers/base_analyzer.py
handsdown/ast_parser/analyzers/class_analyzer.py
handsdown/ast_parser/analyzers/expression_analyzer.py
handsdown/ast_parser/analyzers/function_analyzer.py
handsdown/ast_parser/analyzers/module_analyzer.py
handsdown/ast_parser/module_record_list.py
handsdown/ast_parser/node_records/__init__.py
handsdown/ast_parser/node_records/argument_record.py
handsdown/ast_parser/node_records/attribute_record.py
handsdown/ast_parser/node_records/class_record.py
handsdown/ast_parser/node_records/expression_record.py
handsdown/ast_parser/node_records/function_record.py
handsdown/ast_parser/node_records/import_record.py
handsdown/ast_parser/node_records/module_record.py
handsdown/ast_parser/node_records/node_record.py
handsdown/ast_parser/node_records/text_record.py
handsdown/ast_parser/smart_ast.py
handsdown/ast_parser/type_defs.py
handsdown/cli_parser.py
handsdown/constants.py
handsdown/docs_examples/README.md
handsdown/exceptions.py
handsdown/generators/__init__.py
handsdown/generators/base.py
handsdown/generators/material.py
handsdown/generators/rtd.py
handsdown/jinja_manager.py
handsdown/loader.py
handsdown/main.py
handsdown/md_document.py
handsdown/processors/__init__.py
handsdown/processors/base.py
handsdown/processors/pep257.py
handsdown/processors/rst.py
handsdown/processors/section.py
handsdown/processors/section_block.py
handsdown/processors/section_map.py
handsdown/processors/smart.py
handsdown/py.typed
handsdown/templates/common/argument.py.jinja2
handsdown/templates/common/class.md.jinja2
handsdown/templates/common/class_signature.py.jinja2
handsdown/templates/common/docstring.md.jinja2
handsdown/templates/common/function.md.jinja2
handsdown/templates/common/function_signature.py.jinja2
handsdown/templates/common/gh_pages_config.yml.jinja2
handsdown/templates/common/index.md.jinja2
handsdown-2.1.0.dist-info/LICENSE
handsdown-2.1.0.dist-info/METADATA
handsdown-2.1.0.dist-info/WHEEL
handsdown-2.1.0.dist-info/entry_points.txt
handsdown-2.1.0.dist-info/RECORD
