Metadata-Version: 2.1
Name: handsdown
Version: 2.1.0
Summary: Python docstring-based documentation generator for lazy perfectionists.
Home-page: https://vemel.github.io/handsdown/
License: MIT
Keywords: autodoc,documentation,generator,markdown
Author: Vlad Emelianov
Author-email: vlad.emelianov.nz@gmail.com
Requires-Python: >=3.7,<4.0
Classifier: Development Status :: 5 - Production/Stable
Classifier: Environment :: Console
Classifier: Framework :: Django
Classifier: Framework :: Flask
Classifier: Intended Audience :: Developers
Classifier: License :: OSI Approved :: MIT License
Classifier: Natural Language :: English
Classifier: Operating System :: OS Independent
Classifier: Programming Language :: Python :: 3
Classifier: Programming Language :: Python :: 3.7
Classifier: Programming Language :: Python :: 3.8
Classifier: Programming Language :: Python :: 3.9
Classifier: Programming Language :: Python :: 3.10
Classifier: Programming Language :: Python :: 3.11
Classifier: Programming Language :: Python :: 3.12
Classifier: Programming Language :: Python :: 3 :: Only
Classifier: Programming Language :: Python :: 3.13
Classifier: Programming Language :: Python :: Implementation :: CPython
Classifier: Topic :: Software Development :: Libraries :: Python Modules
Classifier: Typing :: Typed
Requires-Dist: black
Requires-Dist: importlib-resources
Requires-Dist: jinja2
Requires-Dist: pip
Requires-Dist: typed-ast
Project-URL: Bug Tracker, https://github.com/vemel/handsdown/issues
Project-URL: Documentation, https://handsdown.readthedocs.io/en/latest/
Project-URL: Repository, https://github.com/vemel/handsdown
Project-URL: Source, https://github.com/vemel/handsdown
